genrss/__init__.py
genrss/enclosure.py
genrss/image.py
genrss/item.py
genrss/utils.py
genrss-1.0.6.dist-info/LICENSE
genrss-1.0.6.dist-info/METADATA
genrss-1.0.6.dist-info/WHEEL
genrss-1.0.6.dist-info/top_level.txt
genrss-1.0.6.dist-info/RECORD
