Metadata-Version: 2.1
Name: genrss
Version: 1.0.6
Summary: RSS feed generator for python
Home-page: UNKNOWN
Author: Dmitriy Pleshevskiy
Author-email: dmitriy@ideascup.me
License: MIT
Platform: UNKNOWN
Requires-Dist: lxml (>=4.3.4)
Requires-Dist: pytz (==2019.1)
